{
  "posts": [
    {
      "id": 1,
      "title": "json-server",
      "author": "typicode"
    }
  ],
  "comments": [
    {
      "id": 1,
      "body": "some comment",
      "postId": 1
    }
  ],
  "Users": [
    {
      "id": 1,
      "Name": "Some Name",
      "Email": "SomeEmail@gmail.com",
      "Mobile": 1,
      "Age": 1
    },
    {
      "Name": "random user",
      "Email": "random@gmail.com",
      "Mobile": 1231231234,
      "Age": 99,
      "id": 2
    },
    {
      "Name": "array",
      "Email": "array@gmail.com",
      "Mobile": 1234512344,
      "Age": 45,
      "id": 3
    },
    {
      "Name": "your name",
      "Email": "anyeamail@gmail.com",
      "Mobile": 1526231478,
      "Age": 89,
      "id": 4
    }
  ],
  "profile": {
    "name": "typicode"
  }
}